{
    "Arrested_development_why_the_world’s_poorest_are_being_left_behind": {
        "humor_count": 0,
        "total_words": 572,
        "humor_density": 0.0
    },
    "A_new_prescription_Kathy_Willis_on_how_nature_can_improve_your_health": {
        "humor_count": 0,
        "total_words": 650,
        "humor_density": 0.0
    },
    "Ballot_box_bets_What_America's_election_means_for_investors": {
        "humor_count": 0,
        "total_words": 624,
        "humor_density": 0.0
    },
    "Black_boxes_(part_one)_Michael_Kovrig_on_how_he_became_a_political_hostage_in_China": {
        "humor_count": 0,
        "total_words": 536,
        "humor_density": 0.0
    },
    "Bulls’_AI_funding_artificial_intelligence": {
        "humor_count": 0,
        "total_words": 411,
        "humor_density": 0.0
    },
    "Chip_wreck_Intel_is_on_the_rocks": {
        "humor_count": 0,
        "total_words": 499,
        "humor_density": 0.0
    },
    "Come_on_out,_the_vacuum’s_fine_SpaceX": {
        "humor_count": 0,
        "total_words": 520,
        "humor_density": 0.0
    },
    "Election_rejection_fears_of_a_contested_result": {
        "humor_count": 0,
        "total_words": 574,
        "humor_density": 0.0
    },
    "Fed-letter_day_at_last,_a_rate_cut": {
        "humor_count": 0,
        "total_words": 511,
        "humor_density": 0.0
    },
    "Foiled_again_a_second_attempt_on_Trump": {
        "humor_count": 0,
        "total_words": 464,
        "humor_density": 0.0
    },
    "From_exile_to_high_office_one_ambassador's_fifty_years_in_China": {
        "humor_count": 0,
        "total_words": 477,
        "humor_density": 0.0
    },
    "Missile-stop_tour_Zelensky_in_America": {
        "humor_count": 0,
        "total_words": 523,
        "humor_density": 0.0
    },
    "No_right_left_Afghanistan’s_oppressed_women": {
        "humor_count": 0,
        "total_words": 644,
        "humor_density": 0.0
    },
    "Open_to_debate_Harris_and_Trump_clash": {
        "humor_count": 0,
        "total_words": 598,
        "humor_density": 0.0
    },
    "Pager_turn_the_Israel-Hizbullah_conflict_escalates": {
        "humor_count": 0,
        "total_words": 643,
        "humor_density": 0.0
    },
    "Playing_the_fuel_reforming_Nigeria’s_subsidies": {
        "humor_count": 0,
        "total_words": 513,
        "humor_density": 0.0
    },
    "Rocketing_Israel_escalates_Lebanon_conflict": {
        "humor_count": 0,
        "total_words": 458,
        "humor_density": 0.0
    },
    "Screen_time_why_the_world_can’t_get_enough_of_YouTube": {
        "humor_count": 0,
        "total_words": 627,
        "humor_density": 0.0
    },
    "Shun_while_it_lasted_never-Trumpers’_fading_sway": {
        "humor_count": 0,
        "total_words": 629,
        "humor_density": 0.0
    },
    "Silicon_returns_to_Silicon_Valley_chipmaking_enters_a_new_golden_age": {
        "humor_count": 0,
        "total_words": 619,
        "humor_density": 0.0
    },
    "The_Weekend_Intelligence_Detoxified": {
        "humor_count": 0,
        "total_words": 551,
        "humor_density": 0.0
    },
    "The_Weekend_Intelligence_Madridland": {
        "humor_count": 0,
        "total_words": 477,
        "humor_density": 0.0
    },
    "War_or_less_Lebanon_on_the_brink": {
        "humor_count": 0,
        "total_words": 594,
        "humor_density": 0.0
    }
}